vis_fetch.py
uv_fivb_vis-0.1.0.dist-info/METADATA
uv_fivb_vis-0.1.0.dist-info/WHEEL
uv_fivb_vis-0.1.0.dist-info/top_level.txt
uv_fivb_vis-0.1.0.dist-info/RECORD
