Metadata-Version: 2.1
Name: uv-fivb-vis
Version: 0.1.0
Summary: pyfivbvis provides an python client to the FIVB VIS web service system.
Requires-Python: >=3.12
Requires-Dist: bs4 >=0.0.2
Requires-Dist: lxml >=5.3.0
Requires-Dist: pandas >=2.2.3
Requires-Dist: requests >=2.32.3
Requires-Dist: uv >=0.4.27
